elm/__init__.py
elm/api.py
elm/cli.py
elm/elm.py
elm/models.py
elm/core/__init__.py
elm/core/config.py
elm/core/copy.py
elm/core/environment.py
elm/core/exceptions.py
elm/core/generation.py
elm/core/masking.py
elm/core/streaming.py
elm/core/types.py
elm/core/utils.py
elm/core/venv.py
elm/elm_commands/__init__.py
elm/elm_commands/config.py
elm/elm_commands/copy.py
elm/elm_commands/environment.py
elm/elm_commands/generate.py
elm/elm_commands/mask.py
elm/elm_utils/__init__.py
elm/elm_utils/command_utils.py
elm/elm_utils/data_utils.py
elm/elm_utils/db_utils.py
elm/elm_utils/encryption.py
elm/elm_utils/file_lock.py
elm/elm_utils/mask_algorithms.py
elm/elm_utils/random_data.py
elm/elm_utils/variables.py
elm/elm_utils/venv.py
elm_tool-0.1.1.dist-info/METADATA
elm_tool-0.1.1.dist-info/WHEEL
elm_tool-0.1.1.dist-info/entry_points.txt
elm_tool-0.1.1.dist-info/licenses/LICENSE
elm_tool-0.1.1.dist-info/RECORD
