Metadata-Version: 2.4
Name: elm-tool
Version: 0.1.1
Summary: Extract, Load and Mask Tool for Database Operations
Project-URL: Homepage, https://github.com/0m3rF/ELM-tool
Project-URL: Documentation, https://github.com/0m3rF/ELM-tool
Project-URL: Repository, https://github.com/0m3rF/ELM-tool.git
Project-URL: Issues, https://github.com/0m3rF/ELM-tool/issues
Author-email: Ömer Faruk Kırlı <omerfarukkirli@gmail.com>
License-Expression: GPL-3.0-or-later
License-File: LICENSE
Keywords: cross database tool,data anonymization,data extraction,data loading,data masking,data migration,database environment management,database operations,database tool,database utilities,etl tool,test-data-generation
Requires-Python: >=3.7
Requires-Dist: click>=8.0.0
Requires-Dist: configparser>=5.0.0
Requires-Dist: cryptography>=3.4.7
Requires-Dist: faker>=37.4.2
Requires-Dist: pandas>=2.0.0
Requires-Dist: platformdirs>=3.0.0
Requires-Dist: pyyaml>=6.0
Requires-Dist: sqlalchemy>=2.0.0
Provides-Extra: all-db
Requires-Dist: oracledb>=1.0.0; extra == 'all-db'
Requires-Dist: psycopg2-binary>=2.9.1; extra == 'all-db'
Requires-Dist: pymysql>=1.0.2; extra == 'all-db'
Requires-Dist: pyodbc>=4.0.34; extra == 'all-db'
Provides-Extra: mssql
Requires-Dist: pyodbc>=4.0.34; extra == 'mssql'
Provides-Extra: mysql
Requires-Dist: pymysql>=1.0.2; extra == 'mysql'
Provides-Extra: oracle
Requires-Dist: oracledb>=1.0.0; extra == 'oracle'
Provides-Extra: postgres
Requires-Dist: psycopg2-binary>=2.9.1; extra == 'postgres'
